AUTHORS.rst
CONTRIBUTING.rst
HISTORY.rst
LICENSE
MANIFEST.in
README.rst
setup.cfg
setup.py
docs/Makefile
docs/authors.rst
docs/conf.py
docs/contributing.rst
docs/history.rst
docs/index.rst
docs/installation.rst
docs/make.bat
docs/readme.rst
docs/usage.rst
pyremotevbox/VirtualBox_client.py
pyremotevbox/VirtualBox_types.py
pyremotevbox/__init__.py
pyremotevbox/exception.py
pyremotevbox/vbox.py
pyremotevbox.egg-info/PKG-INFO
pyremotevbox.egg-info/SOURCES.txt
pyremotevbox.egg-info/dependency_links.txt
pyremotevbox.egg-info/not-zip-safe
pyremotevbox.egg-info/top_level.txt
pyremotevbox/ZSI/ServiceContainer.py
pyremotevbox/ZSI/ServiceProxy.py
pyremotevbox/ZSI/TC.py
pyremotevbox/ZSI/TCapache.py
pyremotevbox/ZSI/TCcompound.py
pyremotevbox/ZSI/TCnumbers.py
pyremotevbox/ZSI/TCtimes.py
pyremotevbox/ZSI/__init__.py
pyremotevbox/ZSI/address.py
pyremotevbox/ZSI/auth.py
pyremotevbox/ZSI/client.py
pyremotevbox/ZSI/digest_auth.py
pyremotevbox/ZSI/dispatch.py
pyremotevbox/ZSI/fault.py
pyremotevbox/ZSI/parse.py
pyremotevbox/ZSI/resolvers.py
pyremotevbox/ZSI/schema.py
pyremotevbox/ZSI/typeinterpreter.py
pyremotevbox/ZSI/version.py
pyremotevbox/ZSI/writer.py
pyremotevbox/ZSI/generate/__init__.py
pyremotevbox/ZSI/generate/commands.py
pyremotevbox/ZSI/generate/containers.py
pyremotevbox/ZSI/generate/pyclass.py
pyremotevbox/ZSI/generate/utility.py
pyremotevbox/ZSI/generate/wsdl2dispatch.py
pyremotevbox/ZSI/generate/wsdl2python.py
pyremotevbox/ZSI/twisted/WSresource.py
pyremotevbox/ZSI/twisted/WSsecurity.py
pyremotevbox/ZSI/twisted/__init__.py
pyremotevbox/ZSI/twisted/client.py
pyremotevbox/ZSI/twisted/interfaces.py
pyremotevbox/ZSI/twisted/reverse.py
pyremotevbox/ZSI/twisted/wsgi.py
pyremotevbox/ZSI/wstools/Namespaces.py
pyremotevbox/ZSI/wstools/TimeoutSocket.py
pyremotevbox/ZSI/wstools/UserTuple.py
pyremotevbox/ZSI/wstools/Utility.py
pyremotevbox/ZSI/wstools/WSDLTools.py
pyremotevbox/ZSI/wstools/XMLSchema.py
pyremotevbox/ZSI/wstools/XMLname.py
pyremotevbox/ZSI/wstools/__init__.py
pyremotevbox/ZSI/wstools/c14n.py
pyremotevbox/ZSI/wstools/logging.py
tests/__init__.py
tests/test_pyremotevbox.py