Metadata-Version: 1.1
Name: pyremotevbox
Version: 0.5.0
Summary: Python API to talk to a remote VirtualBox using VirtualBox WebService
Home-page: https://github.com/rameshg87/pyremotevbox
Author: Ramakrishnan G
Author-email: rameshg87@gmail.com
License: Apache
Keywords: pyremotevbox
Platform: UNKNOWN
Classifier: Intended Audience :: Developers
Classifier: License :: OSI Approved :: Apache Software License
Classifier: Programming Language :: Python :: 2.7
